gloria/plot.py
gloria/models.py
gloria/interface.py
gloria/__init__.py
gloria/api.py
gloria/regressors.py
gloria/profiles.py
gloria/stan_models/normal.exe
gloria/stan_models/beta_binomial.exe
gloria/stan_models/normal.stan
gloria/stan_models/beta_binomial.stan
gloria/stan_models/beta.stan
gloria/stan_models/gamma.exe
gloria/stan_models/binomial.exe
gloria/stan_models/negative_binomial.stan
gloria/stan_models/beta.exe
gloria/stan_models/poisson.stan
gloria/stan_models/binomial.stan
gloria/stan_models/gamma.stan
gloria/stan_models/negative_binomial.exe
gloria/stan_models/poisson.exe
gloria/stan_models/cmdstan-2.36.0/makefile
gloria/stan_models/cmdstan-2.36.0/bin/stansummary
gloria/stan_models/cmdstan-2.36.0/bin/diagnose
gloria/stan_models/cmdstan-2.36.0/bin/print
gloria/stan_models/cmdstan-2.36.0/bin/stanc
gloria/stan_models/cmdstan-2.36.0/stan/lib/stan_math/lib/tbb_2020.3/third-party-programs.txt
gloria/stan_models/cmdstan-2.36.0/stan/lib/stan_math/lib/tbb_2020.3/index.html
gloria/stan_models/cmdstan-2.36.0/stan/lib/stan_math/lib/tbb_2020.3/LICENSE
gloria/stan_models/cmdstan-2.36.0/stan/lib/stan_math/lib/tbb_2020.3/Makefile
gloria/stan_models/cmdstan-2.36.0/stan/lib/stan_math/lib/tbb_2020.3/CHANGES
gloria/stan_models/cmdstan-2.36.0/stan/lib/stan_math/lib/tbb_2020.3/STAN_CHANGES
gloria/stan_models/cmdstan-2.36.0/stan/lib/stan_math/lib/tbb_2020.3/README
gloria/stan_models/cmdstan-2.36.0/stan/lib/stan_math/lib/tbb_2020.3/README.md
gloria/stan_models/cmdstan-2.36.0/stan/lib/stan_math/lib/tbb_2020.3/.gitignore
gloria/stan_models/cmdstan-2.36.0/stan/lib/stan_math/lib/tbb_2020.3/.gitattributes
gloria/stan_models/cmdstan-2.36.0/stan/lib/stan_math/lib/tbb_2020.3/Doxyfile
gloria/stan_models/cmdstan-2.36.0/stan/lib/stan_math/lib/tbb_2020.3/cmake/TBBBuild.cmake
gloria/stan_models/cmdstan-2.36.0/stan/lib/stan_math/lib/tbb_2020.3/cmake/TBBInstallConfig.cmake
gloria-0.1.2.dist-info/RECORD
gloria-0.1.2.dist-info/WHEEL
gloria-0.1.2.dist-info/top_level.txt
gloria-0.1.2.dist-info/METADATA
gloria-0.1.2.dist-info/licenses/LICENSE
