Metadata-Version: 2.4
Name: gloria
Version: 0.1.2
Summary: Gloria is a modern open-source framework for time series analysis and forecasting.
Author-email: Benjamin Kambs <b.kambs@e-dynamics.de>, Patrik Wollgarten <p.wollgarten@e-dynamics.de>
Project-URL: Homepage, https://www.e-dynamics.de/gloria-open-source-framework/
Project-URL: Documentation, https://e-dyn.github.io/gloria/
Project-URL: Repository, https://github.com/e-dyn/gloria
Classifier: Development Status :: 4 - Beta
Classifier: Operating System :: OS Independent
Classifier: Programming Language :: Python :: 3
Classifier: Programming Language :: Python :: 3.9
Classifier: Programming Language :: Python :: 3.10
Classifier: Programming Language :: Python :: 3.11
Classifier: Programming Language :: Python :: 3.12
Classifier: Intended Audience :: Science/Research
Classifier: Intended Audience :: Developers
Classifier: Intended Audience :: Financial and Insurance Industry
Classifier: Topic :: Scientific/Engineering :: Information Analysis
Requires-Python: <3.13,>=3.9
License-File: LICENSE
Requires-Dist: pandas<3.0.0,>=2.2.3
Requires-Dist: numpy<=2.0.2
Requires-Dist: pydantic<3.0.0,>=2.10.6
Requires-Dist: scipy<=1.13.1
Requires-Dist: matplotlib<=3.9.4
Requires-Dist: cmdstanpy<2.0.0,>=1.2.5
Requires-Dist: holidays<0.68,>=0.67
Requires-Dist: sktime<0.38.0,>=0.37.0
Requires-Dist: tomli<3.0.0,>=2.2.1
Requires-Dist: seaborn<0.14.0,>=0.13.2
Dynamic: license-file
